{
    "description": "",
    "tags": [],
    "size": {
        "height": 6000,
        "width": 4000
    },
    "objects": [
        {
            "id": 44646227,
            "classId": 4668095,
            "description": "",
            "geometryType": "polygon",
            "labelerLogin": "inbox@datasetninja.com",
            "createdAt": "2023-09-15T14:10:10.125Z",
            "updatedAt": "2023-09-15T14:10:10.125Z",
            "tags": [],
            "classTitle": "Tooth",
            "points": {
                "exterior": [
                    [
                        2898,
                        1012
                    ],
                    [
                        2937,
                        1023
                    ],
                    [
                        2999,
                        1018
                    ],
                    [
                        3046,
                        1009
                    ],
                    [
                        3109,
                        981
                    ],
                    [
                        3165,
                        940
                    ],
                    [
                        3209,
                        899
                    ],
                    [
                        3250,
                        855
                    ],
                    [
                        3285,
                        812
                    ],
                    [
                        3318,
                        765
                    ],
                    [
                        3344,
                        709
                    ],
                    [
                        3363,
                        649
                    ],
                    [
                        3365,
                        601
                    ],
                    [
                        3348,
                        552
                    ],
                    [
                        3316,
                        518
                    ],
                    [
                        3284,
                        486
                    ],
                    [
                        3268,
                        458
                    ],
                    [
                        3255,
                        407
                    ],
                    [
                        3222,
                        338
                    ],
                    [
                        3197,
                        292
                    ],
                    [
                        3158,
                        263
                    ],
                    [
                        3112,
                        244
                    ],
                    [
                        3037,
                        225
                    ],
                    [
                        2962,
                        223
                    ],
                    [
                        2865,
                        233
                    ],
                    [
                        2801,
                        247
                    ],
                    [
                        2719,
                        269
                    ],
                    [
                        2647,
                        298
                    ],
                    [
                        2597,
                        333
                    ],
                    [
                        2589,
                        385
                    ],
                    [
                        2594,
                        445
                    ],
                    [
                        2607,
                        496
                    ],
                    [
                        2633,
                        527
                    ],
                    [
                        2680,
                        555
                    ],
                    [
                        2711,
                        577
                    ],
                    [
                        2745,
                        609
                    ],
                    [
                        2761,
                        642
                    ],
                    [
                        2789,
                        692
                    ],
                    [
                        2810,
                        737
                    ],
                    [
                        2827,
                        787
                    ],
                    [
                        2846,
                        831
                    ],
                    [
                        2865,
                        865
                    ],
                    [
                        2883,
                        899
                    ],
                    [
                        2892,
                        951
                    ]
                ],
                "interior": []
            }
        },
        {
            "id": 44646226,
            "classId": 4668095,
            "description": "",
            "geometryType": "polygon",
            "labelerLogin": "inbox@datasetninja.com",
            "createdAt": "2023-09-15T14:10:10.125Z",
            "updatedAt": "2023-09-15T14:10:10.125Z",
            "tags": [],
            "classTitle": "Tooth",
            "points": {
                "exterior": [
                    [
                        1016,
                        4148
                    ],
                    [
                        1097,
                        4127
                    ],
                    [
                        1202,
                        4125
                    ],
                    [
                        1319,
                        4167
                    ],
                    [
                        1359,
                        4265
                    ],
                    [
                        1354,
                        4355
                    ],
                    [
                        1333,
                        4469
                    ],
                    [
                        1334,
                        4614
                    ],
                    [
                        1306,
                        4678
                    ],
                    [
                        1214,
                        4770
                    ],
                    [
                        1168,
                        4802
                    ],
                    [
                        1085,
                        4789
                    ],
                    [
                        1033,
                        4745
                    ],
                    [
                        957,
                        4703
                    ],
                    [
                        897,
                        4668
                    ],
                    [
                        818,
                        4574
                    ],
                    [
                        757,
                        4509
                    ],
                    [
                        724,
                        4471
                    ],
                    [
                        724,
                        4471
                    ],
                    [
                        717,
                        4419
                    ],
                    [
                        709,
                        4329
                    ],
                    [
                        734,
                        4302
                    ],
                    [
                        784,
                        4265
                    ],
                    [
                        841,
                        4265
                    ],
                    [
                        918,
                        4260
                    ],
                    [
                        939,
                        4252
                    ],
                    [
                        982,
                        4225
                    ],
                    [
                        1003,
                        4185
                    ]
                ],
                "interior": []
            }
        },
        {
            "id": 44646225,
            "classId": 4668092,
            "description": "",
            "geometryType": "polygon",
            "labelerLogin": "inbox@datasetninja.com",
            "createdAt": "2023-09-15T14:10:10.125Z",
            "updatedAt": "2023-09-15T14:10:10.125Z",
            "tags": [],
            "classTitle": "Caries",
            "points": {
                "exterior": [
                    [
                        1790,
                        4481
                    ],
                    [
                        1765,
                        4466
                    ],
                    [
                        1782,
                        4481
                    ],
                    [
                        1797,
                        4491
                    ]
                ],
                "interior": []
            }
        },
        {
            "id": 44646224,
            "classId": 4668095,
            "description": "",
            "geometryType": "polygon",
            "labelerLogin": "inbox@datasetninja.com",
            "createdAt": "2023-09-15T14:10:10.124Z",
            "updatedAt": "2023-09-15T14:10:10.124Z",
            "tags": [],
            "classTitle": "Tooth",
            "points": {
                "exterior": [
                    [
                        248,
                        2761
                    ],
                    [
                        282,
                        3010
                    ],
                    [
                        287,
                        3064
                    ],
                    [
                        307,
                        3102
                    ],
                    [
                        332,
                        3127
                    ],
                    [
                        355,
                        3137
                    ],
                    [
                        386,
                        3147
                    ],
                    [
                        434,
                        3152
                    ],
                    [
                        469,
                        3147
                    ],
                    [
                        497,
                        3130
                    ],
                    [
                        533,
                        3107
                    ],
                    [
                        563,
                        3092
                    ],
                    [
                        586,
                        3064
                    ],
                    [
                        619,
                        3021
                    ],
                    [
                        647,
                        2983
                    ],
                    [
                        672,
                        2942
                    ],
                    [
                        703,
                        2904
                    ],
                    [
                        733,
                        2873
                    ],
                    [
                        754,
                        2838
                    ],
                    [
                        774,
                        2797
                    ],
                    [
                        784,
                        2759
                    ],
                    [
                        786,
                        2729
                    ],
                    [
                        789,
                        2693
                    ],
                    [
                        784,
                        2663
                    ],
                    [
                        761,
                        2630
                    ],
                    [
                        736,
                        2594
                    ],
                    [
                        708,
                        2564
                    ],
                    [
                        667,
                        2541
                    ],
                    [
                        632,
                        2518
                    ],
                    [
                        599,
                        2498
                    ],
                    [
                        573,
                        2493
                    ],
                    [
                        523,
                        2478
                    ],
                    [
                        464,
                        2462
                    ],
                    [
                        444,
                        2452
                    ],
                    [
                        396,
                        2442
                    ],
                    [
                        330,
                        2445
                    ],
                    [
                        276,
                        2457
                    ],
                    [
                        231,
                        2485
                    ],
                    [
                        221,
                        2541
                    ],
                    [
                        223,
                        2599
                    ]
                ],
                "interior": []
            }
        },
        {
            "id": 44646223,
            "classId": 4668095,
            "description": "",
            "geometryType": "polygon",
            "labelerLogin": "inbox@datasetninja.com",
            "createdAt": "2023-09-15T14:10:10.124Z",
            "updatedAt": "2023-09-15T14:10:10.124Z",
            "tags": [],
            "classTitle": "Tooth",
            "points": {
                "exterior": [
                    [
                        726,
                        3696
                    ],
                    [
                        707,
                        3730
                    ],
                    [
                        634,
                        3772
                    ],
                    [
                        558,
                        3805
                    ],
                    [
                        517,
                        3880
                    ],
                    [
                        540,
                        4006
                    ],
                    [
                        590,
                        4118
                    ],
                    [
                        692,
                        4196
                    ],
                    [
                        767,
                        4246
                    ],
                    [
                        817,
                        4263
                    ],
                    [
                        920,
                        4261
                    ],
                    [
                        976,
                        4227
                    ],
                    [
                        1014,
                        4150
                    ],
                    [
                        1028,
                        4068
                    ],
                    [
                        1037,
                        3935
                    ],
                    [
                        1033,
                        3799
                    ],
                    [
                        1006,
                        3736
                    ],
                    [
                        947,
                        3699
                    ],
                    [
                        901,
                        3696
                    ],
                    [
                        828,
                        3705
                    ],
                    [
                        792,
                        3715
                    ]
                ],
                "interior": []
            }
        },
        {
            "id": 44646222,
            "classId": 4668092,
            "description": "",
            "geometryType": "polygon",
            "labelerLogin": "inbox@datasetninja.com",
            "createdAt": "2023-09-15T14:10:10.124Z",
            "updatedAt": "2023-09-15T14:10:10.124Z",
            "tags": [],
            "classTitle": "Caries",
            "points": {
                "exterior": [
                    [
                        2332,
                        4656
                    ],
                    [
                        2317,
                        4650
                    ],
                    [
                        2306,
                        4648
                    ],
                    [
                        2304,
                        4651
                    ],
                    [
                        2311,
                        4655
                    ],
                    [
                        2318,
                        4660
                    ],
                    [
                        2326,
                        4661
                    ]
                ],
                "interior": []
            }
        },
        {
            "id": 44646221,
            "classId": 4668092,
            "description": "",
            "geometryType": "polygon",
            "labelerLogin": "inbox@datasetninja.com",
            "createdAt": "2023-09-15T14:10:10.124Z",
            "updatedAt": "2023-09-15T14:10:10.124Z",
            "tags": [],
            "classTitle": "Caries",
            "points": {
                "exterior": [
                    [
                        1775,
                        1096
                    ],
                    [
                        1774,
                        1097
                    ],
                    [
                        1773,
                        1102
                    ],
                    [
                        1772,
                        1107
                    ],
                    [
                        1773,
                        1111
                    ],
                    [
                        1777,
                        1112
                    ],
                    [
                        1782,
                        1109
                    ],
                    [
                        1787,
                        1107
                    ],
                    [
                        1793,
                        1103
                    ],
                    [
                        1793,
                        1099
                    ],
                    [
                        1791,
                        1095
                    ],
                    [
                        1785,
                        1093
                    ],
                    [
                        1776,
                        1091
                    ]
                ],
                "interior": []
            }
        },
        {
            "id": 44646220,
            "classId": 4668095,
            "description": "",
            "geometryType": "polygon",
            "labelerLogin": "inbox@datasetninja.com",
            "createdAt": "2023-09-15T14:10:10.123Z",
            "updatedAt": "2023-09-15T14:10:10.123Z",
            "tags": [],
            "classTitle": "Tooth",
            "points": {
                "exterior": [
                    [
                        2467,
                        4174
                    ],
                    [
                        2536,
                        4138
                    ],
                    [
                        2636,
                        4147
                    ],
                    [
                        2740,
                        4147
                    ],
                    [
                        2832,
                        4152
                    ],
                    [
                        2997,
                        4210
                    ],
                    [
                        3058,
                        4229
                    ],
                    [
                        3111,
                        4290
                    ],
                    [
                        3138,
                        4337
                    ],
                    [
                        3116,
                        4506
                    ],
                    [
                        3094,
                        4611
                    ],
                    [
                        3042,
                        4763
                    ],
                    [
                        3008,
                        4854
                    ],
                    [
                        2912,
                        4923
                    ],
                    [
                        2862,
                        4959
                    ],
                    [
                        2743,
                        4992
                    ],
                    [
                        2569,
                        5022
                    ],
                    [
                        2459,
                        5025
                    ],
                    [
                        2417,
                        4989
                    ],
                    [
                        2390,
                        4906
                    ],
                    [
                        2445,
                        4856
                    ],
                    [
                        2456,
                        4685
                    ],
                    [
                        2442,
                        4539
                    ],
                    [
                        2431,
                        4392
                    ],
                    [
                        2423,
                        4365
                    ],
                    [
                        2439,
                        4265
                    ]
                ],
                "interior": []
            }
        },
        {
            "id": 44646219,
            "classId": 4668095,
            "description": "",
            "geometryType": "polygon",
            "labelerLogin": "inbox@datasetninja.com",
            "createdAt": "2023-09-15T14:10:10.123Z",
            "updatedAt": "2023-09-15T14:10:10.123Z",
            "tags": [],
            "classTitle": "Tooth",
            "points": {
                "exterior": [
                    [
                        1474,
                        4121
                    ],
                    [
                        1409,
                        4181
                    ],
                    [
                        1363,
                        4292
                    ],
                    [
                        1352,
                        4388
                    ],
                    [
                        1331,
                        4486
                    ],
                    [
                        1329,
                        4607
                    ],
                    [
                        1352,
                        4695
                    ],
                    [
                        1405,
                        4787
                    ],
                    [
                        1463,
                        4827
                    ],
                    [
                        1570,
                        4860
                    ],
                    [
                        1695,
                        4845
                    ],
                    [
                        1781,
                        4812
                    ],
                    [
                        1831,
                        4787
                    ],
                    [
                        1896,
                        4772
                    ],
                    [
                        1933,
                        4733
                    ],
                    [
                        1952,
                        4693
                    ],
                    [
                        1946,
                        4605
                    ],
                    [
                        1960,
                        4524
                    ],
                    [
                        1952,
                        4461
                    ],
                    [
                        1904,
                        4382
                    ],
                    [
                        1847,
                        4271
                    ],
                    [
                        1812,
                        4213
                    ],
                    [
                        1714,
                        4125
                    ],
                    [
                        1636,
                        4093
                    ],
                    [
                        1557,
                        4087
                    ]
                ],
                "interior": []
            }
        },
        {
            "id": 44646218,
            "classId": 4668095,
            "description": "",
            "geometryType": "polygon",
            "labelerLogin": "inbox@datasetninja.com",
            "createdAt": "2023-09-15T14:10:10.123Z",
            "updatedAt": "2023-09-15T14:10:10.123Z",
            "tags": [],
            "classTitle": "Tooth",
            "points": {
                "exterior": [
                    [
                        370,
                        3145
                    ],
                    [
                        326,
                        3206
                    ],
                    [
                        314,
                        3316
                    ],
                    [
                        339,
                        3529
                    ],
                    [
                        360,
                        3661
                    ],
                    [
                        423,
                        3767
                    ],
                    [
                        487,
                        3811
                    ],
                    [
                        554,
                        3816
                    ],
                    [
                        665,
                        3763
                    ],
                    [
                        726,
                        3696
                    ],
                    [
                        790,
                        3586
                    ],
                    [
                        849,
                        3504
                    ],
                    [
                        882,
                        3448
                    ],
                    [
                        880,
                        3358
                    ],
                    [
                        840,
                        3279
                    ],
                    [
                        795,
                        3208
                    ],
                    [
                        746,
                        3197
                    ],
                    [
                        659,
                        3132
                    ],
                    [
                        600,
                        3116
                    ],
                    [
                        561,
                        3091
                    ],
                    [
                        500,
                        3136
                    ],
                    [
                        425,
                        3153
                    ]
                ],
                "interior": []
            }
        },
        {
            "id": 44646217,
            "classId": 4668095,
            "description": "",
            "geometryType": "polygon",
            "labelerLogin": "inbox@datasetninja.com",
            "createdAt": "2023-09-15T14:10:10.122Z",
            "updatedAt": "2023-09-15T14:10:10.122Z",
            "tags": [],
            "classTitle": "Tooth",
            "points": {
                "exterior": [
                    [
                        3095,
                        4268
                    ],
                    [
                        3180,
                        4221
                    ],
                    [
                        3293,
                        4215
                    ],
                    [
                        3453,
                        4268
                    ],
                    [
                        3566,
                        4337
                    ],
                    [
                        3630,
                        4437
                    ],
                    [
                        3649,
                        4508
                    ],
                    [
                        3611,
                        4580
                    ],
                    [
                        3577,
                        4666
                    ],
                    [
                        3566,
                        4732
                    ],
                    [
                        3541,
                        4812
                    ],
                    [
                        3503,
                        4890
                    ],
                    [
                        3423,
                        4953
                    ],
                    [
                        3321,
                        4992
                    ],
                    [
                        3263,
                        5017
                    ],
                    [
                        3196,
                        5050
                    ],
                    [
                        3127,
                        5064
                    ],
                    [
                        3058,
                        5044
                    ],
                    [
                        2994,
                        5022
                    ],
                    [
                        2953,
                        5019
                    ],
                    [
                        2917,
                        4961
                    ],
                    [
                        2942,
                        4914
                    ],
                    [
                        3003,
                        4859
                    ],
                    [
                        3058,
                        4721
                    ],
                    [
                        3105,
                        4580
                    ],
                    [
                        3133,
                        4426
                    ],
                    [
                        3141,
                        4318
                    ],
                    [
                        3105,
                        4273
                    ]
                ],
                "interior": []
            }
        },
        {
            "id": 44646216,
            "classId": 4668095,
            "description": "",
            "geometryType": "polygon",
            "labelerLogin": "inbox@datasetninja.com",
            "createdAt": "2023-09-15T14:10:10.122Z",
            "updatedAt": "2023-09-15T14:10:10.122Z",
            "tags": [],
            "classTitle": "Tooth",
            "points": {
                "exterior": [
                    [
                        2022,
                        4196
                    ],
                    [
                        1986,
                        4257
                    ],
                    [
                        1942,
                        4373
                    ],
                    [
                        1928,
                        4426
                    ],
                    [
                        1959,
                        4492
                    ],
                    [
                        1956,
                        4558
                    ],
                    [
                        1945,
                        4613
                    ],
                    [
                        1948,
                        4688
                    ],
                    [
                        1928,
                        4738
                    ],
                    [
                        1884,
                        4771
                    ],
                    [
                        1904,
                        4845
                    ],
                    [
                        1992,
                        4917
                    ],
                    [
                        2080,
                        4942
                    ],
                    [
                        2174,
                        4934
                    ],
                    [
                        2265,
                        4917
                    ],
                    [
                        2379,
                        4884
                    ],
                    [
                        2448,
                        4857
                    ],
                    [
                        2458,
                        4760
                    ],
                    [
                        2455,
                        4648
                    ],
                    [
                        2432,
                        4505
                    ],
                    [
                        2415,
                        4366
                    ],
                    [
                        2381,
                        4286
                    ],
                    [
                        2344,
                        4253
                    ],
                    [
                        2315,
                        4213
                    ],
                    [
                        2244,
                        4184
                    ],
                    [
                        2168,
                        4173
                    ],
                    [
                        2096,
                        4160
                    ]
                ],
                "interior": []
            }
        },
        {
            "id": 44646215,
            "classId": 4668092,
            "description": "",
            "geometryType": "polygon",
            "labelerLogin": "inbox@datasetninja.com",
            "createdAt": "2023-09-15T14:10:10.122Z",
            "updatedAt": "2023-09-15T14:10:10.122Z",
            "tags": [],
            "classTitle": "Caries",
            "points": {
                "exterior": [
                    [
                        1625,
                        4435
                    ],
                    [
                        1600,
                        4435
                    ],
                    [
                        1585,
                        4440
                    ],
                    [
                        1560,
                        4459
                    ],
                    [
                        1536,
                        4481
                    ],
                    [
                        1519,
                        4513
                    ],
                    [
                        1497,
                        4533
                    ],
                    [
                        1498,
                        4543
                    ],
                    [
                        1514,
                        4532
                    ],
                    [
                        1533,
                        4509
                    ],
                    [
                        1559,
                        4476
                    ],
                    [
                        1594,
                        4450
                    ],
                    [
                        1624,
                        4456
                    ],
                    [
                        1648,
                        4450
                    ],
                    [
                        1686,
                        4432
                    ],
                    [
                        1710,
                        4428
                    ],
                    [
                        1733,
                        4445
                    ],
                    [
                        1751,
                        4454
                    ],
                    [
                        1737,
                        4434
                    ],
                    [
                        1710,
                        4417
                    ],
                    [
                        1679,
                        4428
                    ],
                    [
                        1653,
                        4433
                    ]
                ],
                "interior": []
            }
        },
        {
            "id": 44646214,
            "classId": 4668095,
            "description": "",
            "geometryType": "polygon",
            "labelerLogin": "inbox@datasetninja.com",
            "createdAt": "2023-09-15T14:10:10.121Z",
            "updatedAt": "2023-09-15T14:10:10.121Z",
            "tags": [],
            "classTitle": "Tooth",
            "points": {
                "exterior": [
                    [
                        555,
                        1843
                    ],
                    [
                        586,
                        1850
                    ],
                    [
                        627,
                        1866
                    ],
                    [
                        685,
                        1894
                    ],
                    [
                        720,
                        1914
                    ],
                    [
                        745,
                        1934
                    ],
                    [
                        806,
                        1938
                    ],
                    [
                        858,
                        1938
                    ],
                    [
                        949,
                        1903
                    ],
                    [
                        1052,
                        1845
                    ],
                    [
                        1100,
                        1806
                    ],
                    [
                        1129,
                        1759
                    ],
                    [
                        1138,
                        1658
                    ],
                    [
                        1124,
                        1589
                    ],
                    [
                        1104,
                        1543
                    ],
                    [
                        1085,
                        1489
                    ],
                    [
                        1077,
                        1437
                    ],
                    [
                        1049,
                        1368
                    ],
                    [
                        996,
                        1315
                    ],
                    [
                        952,
                        1283
                    ],
                    [
                        874,
                        1277
                    ],
                    [
                        801,
                        1293
                    ],
                    [
                        743,
                        1320
                    ],
                    [
                        664,
                        1359
                    ],
                    [
                        626,
                        1377
                    ],
                    [
                        580,
                        1404
                    ],
                    [
                        558,
                        1440
                    ],
                    [
                        527,
                        1511
                    ],
                    [
                        504,
                        1553
                    ],
                    [
                        485,
                        1583
                    ],
                    [
                        469,
                        1621
                    ],
                    [
                        464,
                        1694
                    ],
                    [
                        483,
                        1740
                    ],
                    [
                        514,
                        1785
                    ]
                ],
                "interior": []
            }
        },
        {
            "id": 44646213,
            "classId": 4668095,
            "description": "",
            "geometryType": "polygon",
            "labelerLogin": "inbox@datasetninja.com",
            "createdAt": "2023-09-15T14:10:10.121Z",
            "updatedAt": "2023-09-15T14:10:10.121Z",
            "tags": [],
            "classTitle": "Tooth",
            "points": {
                "exterior": [
                    [
                        2166,
                        1199
                    ],
                    [
                        2171,
                        1224
                    ],
                    [
                        2204,
                        1267
                    ],
                    [
                        2246,
                        1290
                    ],
                    [
                        2257,
                        1299
                    ],
                    [
                        2327,
                        1305
                    ],
                    [
                        2400,
                        1303
                    ],
                    [
                        2472,
                        1287
                    ],
                    [
                        2543,
                        1271
                    ],
                    [
                        2641,
                        1243
                    ],
                    [
                        2754,
                        1185
                    ],
                    [
                        2844,
                        1122
                    ],
                    [
                        2887,
                        1024
                    ],
                    [
                        2891,
                        952
                    ],
                    [
                        2867,
                        865
                    ],
                    [
                        2831,
                        802
                    ],
                    [
                        2797,
                        739
                    ],
                    [
                        2781,
                        692
                    ],
                    [
                        2746,
                        624
                    ],
                    [
                        2708,
                        586
                    ],
                    [
                        2666,
                        547
                    ],
                    [
                        2595,
                        503
                    ],
                    [
                        2500,
                        451
                    ],
                    [
                        2429,
                        429
                    ],
                    [
                        2356,
                        424
                    ],
                    [
                        2272,
                        430
                    ],
                    [
                        2157,
                        452
                    ],
                    [
                        2105,
                        484
                    ],
                    [
                        2047,
                        531
                    ],
                    [
                        2028,
                        570
                    ],
                    [
                        2016,
                        635
                    ],
                    [
                        2010,
                        697
                    ],
                    [
                        2010,
                        735
                    ],
                    [
                        2012,
                        747
                    ],
                    [
                        2062,
                        774
                    ],
                    [
                        2095,
                        800
                    ],
                    [
                        2125,
                        850
                    ],
                    [
                        2139,
                        883
                    ],
                    [
                        2152,
                        938
                    ],
                    [
                        2154,
                        1025
                    ],
                    [
                        2158,
                        1135
                    ]
                ],
                "interior": []
            }
        },
        {
            "id": 44646212,
            "classId": 4668095,
            "description": "",
            "geometryType": "polygon",
            "labelerLogin": "inbox@datasetninja.com",
            "createdAt": "2023-09-15T14:10:10.121Z",
            "updatedAt": "2023-09-15T14:10:10.121Z",
            "tags": [],
            "classTitle": "Tooth",
            "points": {
                "exterior": [
                    [
                        437,
                        2442
                    ],
                    [
                        467,
                        2458
                    ],
                    [
                        509,
                        2470
                    ],
                    [
                        553,
                        2479
                    ],
                    [
                        594,
                        2474
                    ],
                    [
                        655,
                        2447
                    ],
                    [
                        719,
                        2400
                    ],
                    [
                        758,
                        2366
                    ],
                    [
                        800,
                        2327
                    ],
                    [
                        826,
                        2301
                    ],
                    [
                        846,
                        2255
                    ],
                    [
                        844,
                        2218
                    ],
                    [
                        830,
                        2192
                    ],
                    [
                        825,
                        2158
                    ],
                    [
                        825,
                        2148
                    ],
                    [
                        835,
                        2127
                    ],
                    [
                        832,
                        2093
                    ],
                    [
                        782,
                        2003
                    ],
                    [
                        752,
                        1957
                    ],
                    [
                        731,
                        1929
                    ],
                    [
                        701,
                        1905
                    ],
                    [
                        655,
                        1882
                    ],
                    [
                        603,
                        1866
                    ],
                    [
                        543,
                        1868
                    ],
                    [
                        474,
                        1891
                    ],
                    [
                        428,
                        1920
                    ],
                    [
                        382,
                        1968
                    ],
                    [
                        359,
                        2000
                    ],
                    [
                        333,
                        2060
                    ],
                    [
                        324,
                        2109
                    ],
                    [
                        324,
                        2158
                    ],
                    [
                        324,
                        2190
                    ],
                    [
                        329,
                        2234
                    ],
                    [
                        331,
                        2271
                    ],
                    [
                        335,
                        2324
                    ],
                    [
                        349,
                        2349
                    ],
                    [
                        372,
                        2389
                    ]
                ],
                "interior": []
            }
        },
        {
            "id": 44646211,
            "classId": 4668092,
            "description": "",
            "geometryType": "polygon",
            "labelerLogin": "inbox@datasetninja.com",
            "createdAt": "2023-09-15T14:10:10.121Z",
            "updatedAt": "2023-09-15T14:10:10.121Z",
            "tags": [],
            "classTitle": "Caries",
            "points": {
                "exterior": [
                    [
                        1821,
                        4520
                    ],
                    [
                        1808,
                        4505
                    ],
                    [
                        1803,
                        4509
                    ],
                    [
                        1814,
                        4528
                    ],
                    [
                        1832,
                        4538
                    ],
                    [
                        1844,
                        4538
                    ]
                ],
                "interior": []
            }
        },
        {
            "id": 44646210,
            "classId": 4668095,
            "description": "",
            "geometryType": "polygon",
            "labelerLogin": "inbox@datasetninja.com",
            "createdAt": "2023-09-15T14:10:10.121Z",
            "updatedAt": "2023-09-15T14:10:10.121Z",
            "tags": [],
            "classTitle": "Tooth",
            "points": {
                "exterior": [
                    [
                        1028,
                        1330
                    ],
                    [
                        1032,
                        1339
                    ],
                    [
                        1044,
                        1361
                    ],
                    [
                        1059,
                        1387
                    ],
                    [
                        1071,
                        1414
                    ],
                    [
                        1081,
                        1448
                    ],
                    [
                        1091,
                        1484
                    ],
                    [
                        1104,
                        1527
                    ],
                    [
                        1124,
                        1571
                    ],
                    [
                        1151,
                        1621
                    ],
                    [
                        1179,
                        1662
                    ],
                    [
                        1216,
                        1699
                    ],
                    [
                        1254,
                        1727
                    ],
                    [
                        1279,
                        1737
                    ],
                    [
                        1325,
                        1738
                    ],
                    [
                        1391,
                        1735
                    ],
                    [
                        1447,
                        1727
                    ],
                    [
                        1521,
                        1682
                    ],
                    [
                        1571,
                        1641
                    ],
                    [
                        1607,
                        1591
                    ],
                    [
                        1620,
                        1552
                    ],
                    [
                        1626,
                        1487
                    ],
                    [
                        1648,
                        1377
                    ],
                    [
                        1665,
                        1320
                    ],
                    [
                        1668,
                        1271
                    ],
                    [
                        1667,
                        1223
                    ],
                    [
                        1652,
                        1163
                    ],
                    [
                        1630,
                        1110
                    ],
                    [
                        1610,
                        1079
                    ],
                    [
                        1560,
                        1023
                    ],
                    [
                        1513,
                        1003
                    ],
                    [
                        1458,
                        992
                    ],
                    [
                        1417,
                        985
                    ],
                    [
                        1361,
                        976
                    ],
                    [
                        1288,
                        967
                    ],
                    [
                        1229,
                        972
                    ],
                    [
                        1146,
                        988
                    ],
                    [
                        1088,
                        1029
                    ],
                    [
                        1041,
                        1067
                    ],
                    [
                        1022,
                        1110
                    ],
                    [
                        1013,
                        1173
                    ],
                    [
                        1008,
                        1219
                    ],
                    [
                        1012,
                        1257
                    ],
                    [
                        1013,
                        1277
                    ]
                ],
                "interior": []
            }
        }
    ]
}