{
    "description": "",
    "tags": [],
    "size": {
        "height": 660,
        "width": 1097
    },
    "objects": [
        {
            "id": 44645816,
            "classId": 4668093,
            "description": "",
            "geometryType": "polygon",
            "labelerLogin": "inbox@datasetninja.com",
            "createdAt": "2023-09-15T14:10:07.265Z",
            "updatedAt": "2023-09-15T14:10:07.265Z",
            "tags": [],
            "classTitle": "Cavity",
            "points": {
                "exterior": [
                    [
                        666,
                        105
                    ],
                    [
                        659,
                        116
                    ],
                    [
                        659,
                        139
                    ],
                    [
                        670,
                        159
                    ],
                    [
                        683,
                        174
                    ],
                    [
                        693,
                        166
                    ],
                    [
                        702,
                        164
                    ],
                    [
                        728,
                        162
                    ],
                    [
                        737,
                        153
                    ],
                    [
                        757,
                        138
                    ],
                    [
                        772,
                        127
                    ],
                    [
                        785,
                        118
                    ],
                    [
                        795,
                        109
                    ],
                    [
                        789,
                        99
                    ],
                    [
                        776,
                        91
                    ],
                    [
                        752,
                        93
                    ],
                    [
                        725,
                        95
                    ],
                    [
                        692,
                        89
                    ],
                    [
                        682,
                        92
                    ]
                ],
                "interior": []
            }
        },
        {
            "id": 44645815,
            "classId": 4668093,
            "description": "",
            "geometryType": "polygon",
            "labelerLogin": "inbox@datasetninja.com",
            "createdAt": "2023-09-15T14:10:07.264Z",
            "updatedAt": "2023-09-15T14:10:07.264Z",
            "tags": [],
            "classTitle": "Cavity",
            "points": {
                "exterior": [
                    [
                        180,
                        246
                    ],
                    [
                        162,
                        267
                    ],
                    [
                        151,
                        318
                    ],
                    [
                        146,
                        330
                    ],
                    [
                        129,
                        329
                    ],
                    [
                        104,
                        345
                    ],
                    [
                        87,
                        346
                    ],
                    [
                        84,
                        352
                    ],
                    [
                        99,
                        383
                    ],
                    [
                        111,
                        438
                    ],
                    [
                        125,
                        469
                    ],
                    [
                        122,
                        425
                    ],
                    [
                        146,
                        414
                    ],
                    [
                        172,
                        406
                    ],
                    [
                        176,
                        379
                    ],
                    [
                        172,
                        363
                    ],
                    [
                        191,
                        357
                    ],
                    [
                        220,
                        362
                    ],
                    [
                        235,
                        384
                    ],
                    [
                        256,
                        401
                    ],
                    [
                        276,
                        418
                    ],
                    [
                        272,
                        436
                    ],
                    [
                        269,
                        482
                    ],
                    [
                        273,
                        487
                    ],
                    [
                        284,
                        454
                    ],
                    [
                        306,
                        432
                    ],
                    [
                        326,
                        422
                    ],
                    [
                        325,
                        404
                    ],
                    [
                        348,
                        389
                    ],
                    [
                        367,
                        368
                    ],
                    [
                        400,
                        362
                    ],
                    [
                        409,
                        343
                    ],
                    [
                        404,
                        322
                    ],
                    [
                        387,
                        309
                    ],
                    [
                        372,
                        299
                    ],
                    [
                        358,
                        286
                    ],
                    [
                        336,
                        289
                    ],
                    [
                        312,
                        299
                    ],
                    [
                        294,
                        296
                    ],
                    [
                        271,
                        285
                    ],
                    [
                        241,
                        287
                    ],
                    [
                        221,
                        285
                    ],
                    [
                        209,
                        265
                    ],
                    [
                        206,
                        252
                    ],
                    [
                        198,
                        243
                    ]
                ],
                "interior": []
            }
        },
        {
            "id": 44645814,
            "classId": 4668095,
            "description": "",
            "geometryType": "polygon",
            "labelerLogin": "inbox@datasetninja.com",
            "createdAt": "2023-09-15T14:10:07.264Z",
            "updatedAt": "2023-09-15T14:10:07.264Z",
            "tags": [],
            "classTitle": "Tooth",
            "points": {
                "exterior": [
                    [
                        184,
                        103
                    ],
                    [
                        170,
                        111
                    ],
                    [
                        141,
                        129
                    ],
                    [
                        102,
                        148
                    ],
                    [
                        91,
                        172
                    ],
                    [
                        77,
                        199
                    ],
                    [
                        61,
                        249
                    ],
                    [
                        65,
                        292
                    ],
                    [
                        79,
                        346
                    ],
                    [
                        98,
                        388
                    ],
                    [
                        109,
                        430
                    ],
                    [
                        121,
                        467
                    ],
                    [
                        138,
                        502
                    ],
                    [
                        163,
                        530
                    ],
                    [
                        207,
                        553
                    ],
                    [
                        256,
                        565
                    ],
                    [
                        300,
                        575
                    ],
                    [
                        361,
                        586
                    ],
                    [
                        410,
                        595
                    ],
                    [
                        452,
                        598
                    ],
                    [
                        497,
                        587
                    ],
                    [
                        529,
                        541
                    ],
                    [
                        523,
                        506
                    ],
                    [
                        536,
                        450
                    ],
                    [
                        540,
                        407
                    ],
                    [
                        518,
                        360
                    ],
                    [
                        505,
                        313
                    ],
                    [
                        499,
                        268
                    ],
                    [
                        499,
                        223
                    ],
                    [
                        518,
                        186
                    ],
                    [
                        522,
                        158
                    ],
                    [
                        514,
                        105
                    ],
                    [
                        497,
                        74
                    ],
                    [
                        473,
                        70
                    ],
                    [
                        430,
                        78
                    ],
                    [
                        393,
                        77
                    ],
                    [
                        352,
                        73
                    ],
                    [
                        261,
                        87
                    ],
                    [
                        230,
                        94
                    ],
                    [
                        188,
                        103
                    ]
                ],
                "interior": []
            }
        },
        {
            "id": 44645813,
            "classId": 4668095,
            "description": "",
            "geometryType": "polygon",
            "labelerLogin": "inbox@datasetninja.com",
            "createdAt": "2023-09-15T14:10:07.264Z",
            "updatedAt": "2023-09-15T14:10:07.264Z",
            "tags": [],
            "classTitle": "Tooth",
            "points": {
                "exterior": [
                    [
                        629,
                        90
                    ],
                    [
                        598,
                        103
                    ],
                    [
                        548,
                        133
                    ],
                    [
                        531,
                        148
                    ],
                    [
                        522,
                        177
                    ],
                    [
                        514,
                        201
                    ],
                    [
                        501,
                        224
                    ],
                    [
                        497,
                        258
                    ],
                    [
                        509,
                        303
                    ],
                    [
                        526,
                        360
                    ],
                    [
                        532,
                        403
                    ],
                    [
                        553,
                        424
                    ],
                    [
                        568,
                        455
                    ],
                    [
                        589,
                        484
                    ],
                    [
                        634,
                        523
                    ],
                    [
                        680,
                        555
                    ],
                    [
                        782,
                        590
                    ],
                    [
                        844,
                        601
                    ],
                    [
                        917,
                        575
                    ],
                    [
                        942,
                        554
                    ],
                    [
                        973,
                        523
                    ],
                    [
                        981,
                        505
                    ],
                    [
                        1003,
                        447
                    ],
                    [
                        1008,
                        386
                    ],
                    [
                        1009,
                        333
                    ],
                    [
                        1004,
                        291
                    ],
                    [
                        985,
                        222
                    ],
                    [
                        957,
                        154
                    ],
                    [
                        931,
                        107
                    ],
                    [
                        898,
                        77
                    ],
                    [
                        858,
                        55
                    ],
                    [
                        820,
                        56
                    ],
                    [
                        778,
                        60
                    ],
                    [
                        732,
                        69
                    ],
                    [
                        691,
                        80
                    ],
                    [
                        657,
                        86
                    ],
                    [
                        625,
                        90
                    ]
                ],
                "interior": []
            }
        },
        {
            "id": 44645812,
            "classId": 4668092,
            "description": "",
            "geometryType": "polygon",
            "labelerLogin": "inbox@datasetninja.com",
            "createdAt": "2023-09-15T14:10:07.264Z",
            "updatedAt": "2023-09-15T14:10:07.264Z",
            "tags": [],
            "classTitle": "Caries",
            "points": {
                "exterior": [
                    [
                        888,
                        408
                    ],
                    [
                        885,
                        402
                    ],
                    [
                        880,
                        396
                    ],
                    [
                        872,
                        394
                    ],
                    [
                        867,
                        399
                    ],
                    [
                        861,
                        402
                    ],
                    [
                        858,
                        405
                    ],
                    [
                        859,
                        409
                    ],
                    [
                        860,
                        414
                    ],
                    [
                        862,
                        417
                    ],
                    [
                        865,
                        419
                    ],
                    [
                        868,
                        415
                    ],
                    [
                        870,
                        412
                    ],
                    [
                        871,
                        406
                    ],
                    [
                        872,
                        402
                    ],
                    [
                        874,
                        401
                    ],
                    [
                        876,
                        404
                    ],
                    [
                        876,
                        407
                    ],
                    [
                        875,
                        408
                    ],
                    [
                        874,
                        410
                    ],
                    [
                        876,
                        412
                    ],
                    [
                        879,
                        412
                    ],
                    [
                        882,
                        412
                    ],
                    [
                        885,
                        412
                    ],
                    [
                        888,
                        412
                    ]
                ],
                "interior": []
            }
        },
        {
            "id": 44645811,
            "classId": 4668092,
            "description": "",
            "geometryType": "polygon",
            "labelerLogin": "inbox@datasetninja.com",
            "createdAt": "2023-09-15T14:10:07.264Z",
            "updatedAt": "2023-09-15T14:10:07.264Z",
            "tags": [],
            "classTitle": "Caries",
            "points": {
                "exterior": [
                    [
                        874,
                        425
                    ],
                    [
                        875,
                        420
                    ],
                    [
                        872,
                        419
                    ],
                    [
                        869,
                        421
                    ],
                    [
                        868,
                        423
                    ],
                    [
                        868,
                        427
                    ],
                    [
                        868,
                        430
                    ],
                    [
                        871,
                        431
                    ],
                    [
                        874,
                        428
                    ]
                ],
                "interior": []
            }
        },
        {
            "id": 44645810,
            "classId": 4668093,
            "description": "",
            "geometryType": "polygon",
            "labelerLogin": "inbox@datasetninja.com",
            "createdAt": "2023-09-15T14:10:07.263Z",
            "updatedAt": "2023-09-15T14:10:07.263Z",
            "tags": [],
            "classTitle": "Cavity",
            "points": {
                "exterior": [
                    [
                        181,
                        121
                    ],
                    [
                        185,
                        148
                    ],
                    [
                        192,
                        188
                    ],
                    [
                        201,
                        212
                    ],
                    [
                        204,
                        204
                    ],
                    [
                        233,
                        191
                    ],
                    [
                        253,
                        172
                    ],
                    [
                        294,
                        138
                    ],
                    [
                        326,
                        116
                    ],
                    [
                        341,
                        98
                    ],
                    [
                        317,
                        88
                    ],
                    [
                        282,
                        88
                    ],
                    [
                        251,
                        92
                    ],
                    [
                        212,
                        99
                    ],
                    [
                        189,
                        105
                    ]
                ],
                "interior": []
            }
        },
        {
            "id": 44645809,
            "classId": 4668092,
            "description": "",
            "geometryType": "polygon",
            "labelerLogin": "inbox@datasetninja.com",
            "createdAt": "2023-09-15T14:10:07.263Z",
            "updatedAt": "2023-09-15T14:10:07.263Z",
            "tags": [],
            "classTitle": "Caries",
            "points": {
                "exterior": [
                    [
                        879,
                        424
                    ],
                    [
                        878,
                        426
                    ],
                    [
                        877,
                        429
                    ],
                    [
                        878,
                        431
                    ],
                    [
                        881,
                        431
                    ],
                    [
                        883,
                        430
                    ],
                    [
                        884,
                        426
                    ],
                    [
                        883,
                        423
                    ]
                ],
                "interior": []
            }
        },
        {
            "id": 44645808,
            "classId": 4668093,
            "description": "",
            "geometryType": "polygon",
            "labelerLogin": "inbox@datasetninja.com",
            "createdAt": "2023-09-15T14:10:07.263Z",
            "updatedAt": "2023-09-15T14:10:07.263Z",
            "tags": [],
            "classTitle": "Cavity",
            "points": {
                "exterior": [
                    [
                        679,
                        199
                    ],
                    [
                        653,
                        214
                    ],
                    [
                        627,
                        242
                    ],
                    [
                        611,
                        269
                    ],
                    [
                        599,
                        299
                    ],
                    [
                        595,
                        327
                    ],
                    [
                        567,
                        322
                    ],
                    [
                        527,
                        333
                    ],
                    [
                        522,
                        337
                    ],
                    [
                        532,
                        377
                    ],
                    [
                        545,
                        403
                    ],
                    [
                        560,
                        429
                    ],
                    [
                        578,
                        457
                    ],
                    [
                        594,
                        451
                    ],
                    [
                        622,
                        422
                    ],
                    [
                        638,
                        401
                    ],
                    [
                        644,
                        366
                    ],
                    [
                        652,
                        341
                    ],
                    [
                        656,
                        332
                    ],
                    [
                        676,
                        329
                    ],
                    [
                        694,
                        334
                    ],
                    [
                        707,
                        354
                    ],
                    [
                        719,
                        370
                    ],
                    [
                        733,
                        390
                    ],
                    [
                        749,
                        418
                    ],
                    [
                        768,
                        439
                    ],
                    [
                        783,
                        443
                    ],
                    [
                        802,
                        425
                    ],
                    [
                        809,
                        412
                    ],
                    [
                        819,
                        386
                    ],
                    [
                        838,
                        368
                    ],
                    [
                        868,
                        351
                    ],
                    [
                        893,
                        332
                    ],
                    [
                        912,
                        313
                    ],
                    [
                        920,
                        294
                    ],
                    [
                        916,
                        263
                    ],
                    [
                        905,
                        249
                    ],
                    [
                        876,
                        248
                    ],
                    [
                        840,
                        255
                    ],
                    [
                        816,
                        261
                    ],
                    [
                        775,
                        276
                    ],
                    [
                        741,
                        280
                    ],
                    [
                        719,
                        272
                    ],
                    [
                        715,
                        256
                    ],
                    [
                        709,
                        240
                    ],
                    [
                        706,
                        231
                    ],
                    [
                        700,
                        215
                    ],
                    [
                        696,
                        205
                    ]
                ],
                "interior": []
            }
        }
    ]
}