{
    "description": "",
    "tags": [],
    "size": {
        "height": 600,
        "width": 900
    },
    "objects": [
        {
            "id": 44642840,
            "classId": 4668095,
            "description": "",
            "geometryType": "polygon",
            "labelerLogin": "inbox@datasetninja.com",
            "createdAt": "2023-09-15T14:10:00.757Z",
            "updatedAt": "2023-09-15T14:10:00.757Z",
            "tags": [],
            "classTitle": "Tooth",
            "points": {
                "exterior": [
                    [
                        49,
                        362
                    ],
                    [
                        43,
                        385
                    ],
                    [
                        31,
                        410
                    ],
                    [
                        30,
                        432
                    ],
                    [
                        35,
                        454
                    ],
                    [
                        36,
                        468
                    ],
                    [
                        35,
                        481
                    ],
                    [
                        67,
                        500
                    ],
                    [
                        86,
                        501
                    ],
                    [
                        110,
                        491
                    ],
                    [
                        126,
                        478
                    ],
                    [
                        137,
                        466
                    ],
                    [
                        148,
                        451
                    ],
                    [
                        158,
                        439
                    ],
                    [
                        162,
                        409
                    ],
                    [
                        152,
                        389
                    ],
                    [
                        141,
                        367
                    ],
                    [
                        126,
                        343
                    ],
                    [
                        99,
                        333
                    ],
                    [
                        80,
                        334
                    ],
                    [
                        65,
                        340
                    ]
                ],
                "interior": []
            }
        },
        {
            "id": 44642839,
            "classId": 4668092,
            "description": "",
            "geometryType": "polygon",
            "labelerLogin": "inbox@datasetninja.com",
            "createdAt": "2023-09-15T14:10:00.757Z",
            "updatedAt": "2023-09-15T14:10:00.757Z",
            "tags": [],
            "classTitle": "Caries",
            "points": {
                "exterior": [
                    [
                        666,
                        321
                    ],
                    [
                        672,
                        326
                    ],
                    [
                        677,
                        331
                    ],
                    [
                        681,
                        331
                    ],
                    [
                        685,
                        329
                    ],
                    [
                        689,
                        328
                    ],
                    [
                        690,
                        324
                    ],
                    [
                        684,
                        321
                    ],
                    [
                        679,
                        321
                    ],
                    [
                        673,
                        321
                    ]
                ],
                "interior": []
            }
        },
        {
            "id": 44642838,
            "classId": 4668092,
            "description": "",
            "geometryType": "polygon",
            "labelerLogin": "inbox@datasetninja.com",
            "createdAt": "2023-09-15T14:10:00.757Z",
            "updatedAt": "2023-09-15T14:10:00.757Z",
            "tags": [],
            "classTitle": "Caries",
            "points": {
                "exterior": [
                    [
                        121,
                        441
                    ],
                    [
                        115,
                        443
                    ],
                    [
                        106,
                        444
                    ],
                    [
                        102,
                        445
                    ],
                    [
                        106,
                        448
                    ],
                    [
                        113,
                        447
                    ],
                    [
                        117,
                        446
                    ],
                    [
                        122,
                        444
                    ]
                ],
                "interior": []
            }
        },
        {
            "id": 44642837,
            "classId": 4668092,
            "description": "",
            "geometryType": "polygon",
            "labelerLogin": "inbox@datasetninja.com",
            "createdAt": "2023-09-15T14:10:00.757Z",
            "updatedAt": "2023-09-15T14:10:00.757Z",
            "tags": [],
            "classTitle": "Caries",
            "points": {
                "exterior": [
                    [
                        644,
                        306
                    ],
                    [
                        641,
                        316
                    ],
                    [
                        637,
                        323
                    ],
                    [
                        634,
                        329
                    ],
                    [
                        635,
                        334
                    ],
                    [
                        633,
                        340
                    ],
                    [
                        638,
                        346
                    ],
                    [
                        647,
                        350
                    ],
                    [
                        655,
                        351
                    ],
                    [
                        657,
                        346
                    ],
                    [
                        661,
                        339
                    ],
                    [
                        661,
                        337
                    ],
                    [
                        654,
                        336
                    ],
                    [
                        650,
                        333
                    ],
                    [
                        652,
                        330
                    ],
                    [
                        655,
                        329
                    ],
                    [
                        657,
                        327
                    ],
                    [
                        657,
                        322
                    ],
                    [
                        660,
                        315
                    ],
                    [
                        665,
                        310
                    ],
                    [
                        667,
                        305
                    ],
                    [
                        668,
                        302
                    ],
                    [
                        665,
                        297
                    ],
                    [
                        660,
                        294
                    ],
                    [
                        655,
                        297
                    ],
                    [
                        652,
                        302
                    ],
                    [
                        650,
                        304
                    ],
                    [
                        646,
                        305
                    ]
                ],
                "interior": []
            }
        },
        {
            "id": 44642836,
            "classId": 4668092,
            "description": "",
            "geometryType": "polygon",
            "labelerLogin": "inbox@datasetninja.com",
            "createdAt": "2023-09-15T14:10:00.756Z",
            "updatedAt": "2023-09-15T14:10:00.756Z",
            "tags": [],
            "classTitle": "Caries",
            "points": {
                "exterior": [
                    [
                        71,
                        439
                    ],
                    [
                        68,
                        439
                    ],
                    [
                        63,
                        442
                    ],
                    [
                        62,
                        444
                    ],
                    [
                        65,
                        443
                    ],
                    [
                        68,
                        444
                    ],
                    [
                        71,
                        446
                    ],
                    [
                        72,
                        443
                    ]
                ],
                "interior": []
            }
        },
        {
            "id": 44642835,
            "classId": 4668095,
            "description": "",
            "geometryType": "polygon",
            "labelerLogin": "inbox@datasetninja.com",
            "createdAt": "2023-09-15T14:10:00.756Z",
            "updatedAt": "2023-09-15T14:10:00.756Z",
            "tags": [],
            "classTitle": "Tooth",
            "points": {
                "exterior": [
                    [
                        587,
                        404
                    ],
                    [
                        584,
                        429
                    ],
                    [
                        615,
                        450
                    ],
                    [
                        642,
                        448
                    ],
                    [
                        665,
                        432
                    ],
                    [
                        684,
                        413
                    ],
                    [
                        692,
                        400
                    ],
                    [
                        691,
                        378
                    ],
                    [
                        698,
                        359
                    ],
                    [
                        700,
                        341
                    ],
                    [
                        693,
                        324
                    ],
                    [
                        693,
                        309
                    ],
                    [
                        692,
                        294
                    ],
                    [
                        677,
                        285
                    ],
                    [
                        657,
                        279
                    ],
                    [
                        642,
                        266
                    ],
                    [
                        618,
                        265
                    ],
                    [
                        597,
                        263
                    ],
                    [
                        579,
                        269
                    ],
                    [
                        571,
                        273
                    ],
                    [
                        582,
                        300
                    ],
                    [
                        599,
                        350
                    ],
                    [
                        598,
                        385
                    ]
                ],
                "interior": []
            }
        },
        {
            "id": 44642834,
            "classId": 4668095,
            "description": "",
            "geometryType": "polygon",
            "labelerLogin": "inbox@datasetninja.com",
            "createdAt": "2023-09-15T14:10:00.755Z",
            "updatedAt": "2023-09-15T14:10:00.755Z",
            "tags": [],
            "classTitle": "Tooth",
            "points": {
                "exterior": [
                    [
                        418,
                        266
                    ],
                    [
                        417,
                        287
                    ],
                    [
                        422,
                        311
                    ],
                    [
                        428,
                        320
                    ],
                    [
                        440,
                        364
                    ],
                    [
                        449,
                        407
                    ],
                    [
                        445,
                        424
                    ],
                    [
                        467,
                        439
                    ],
                    [
                        503,
                        446
                    ],
                    [
                        556,
                        429
                    ],
                    [
                        579,
                        410
                    ],
                    [
                        597,
                        385
                    ],
                    [
                        598,
                        352
                    ],
                    [
                        584,
                        304
                    ],
                    [
                        565,
                        270
                    ],
                    [
                        533,
                        257
                    ],
                    [
                        510,
                        252
                    ],
                    [
                        489,
                        241
                    ],
                    [
                        451,
                        238
                    ],
                    [
                        434,
                        247
                    ]
                ],
                "interior": []
            }
        },
        {
            "id": 44642833,
            "classId": 4668095,
            "description": "",
            "geometryType": "polygon",
            "labelerLogin": "inbox@datasetninja.com",
            "createdAt": "2023-09-15T14:10:00.755Z",
            "updatedAt": "2023-09-15T14:10:00.755Z",
            "tags": [],
            "classTitle": "Tooth",
            "points": {
                "exterior": [
                    [
                        279,
                        275
                    ],
                    [
                        267,
                        301
                    ],
                    [
                        260,
                        326
                    ],
                    [
                        259,
                        341
                    ],
                    [
                        274,
                        363
                    ],
                    [
                        274,
                        390
                    ],
                    [
                        263,
                        414
                    ],
                    [
                        271,
                        447
                    ],
                    [
                        298,
                        476
                    ],
                    [
                        319,
                        485
                    ],
                    [
                        344,
                        478
                    ],
                    [
                        354,
                        469
                    ],
                    [
                        399,
                        466
                    ],
                    [
                        435,
                        445
                    ],
                    [
                        447,
                        411
                    ],
                    [
                        439,
                        359
                    ],
                    [
                        427,
                        319
                    ],
                    [
                        413,
                        299
                    ],
                    [
                        379,
                        278
                    ],
                    [
                        351,
                        264
                    ],
                    [
                        320,
                        260
                    ],
                    [
                        296,
                        263
                    ]
                ],
                "interior": []
            }
        },
        {
            "id": 44642832,
            "classId": 4668095,
            "description": "",
            "geometryType": "polygon",
            "labelerLogin": "inbox@datasetninja.com",
            "createdAt": "2023-09-15T14:10:00.755Z",
            "updatedAt": "2023-09-15T14:10:00.755Z",
            "tags": [],
            "classTitle": "Tooth",
            "points": {
                "exterior": [
                    [
                        179,
                        325
                    ],
                    [
                        161,
                        353
                    ],
                    [
                        156,
                        394
                    ],
                    [
                        162,
                        413
                    ],
                    [
                        157,
                        443
                    ],
                    [
                        189,
                        466
                    ],
                    [
                        211,
                        471
                    ],
                    [
                        231,
                        462
                    ],
                    [
                        246,
                        447
                    ],
                    [
                        258,
                        424
                    ],
                    [
                        275,
                        389
                    ],
                    [
                        275,
                        364
                    ],
                    [
                        262,
                        346
                    ],
                    [
                        249,
                        331
                    ],
                    [
                        235,
                        316
                    ],
                    [
                        219,
                        308
                    ],
                    [
                        202,
                        308
                    ],
                    [
                        195,
                        312
                    ]
                ],
                "interior": []
            }
        },
        {
            "id": 44642831,
            "classId": 4668092,
            "description": "",
            "geometryType": "polygon",
            "labelerLogin": "inbox@datasetninja.com",
            "createdAt": "2023-09-15T14:10:00.754Z",
            "updatedAt": "2023-09-15T14:10:00.754Z",
            "tags": [],
            "classTitle": "Caries",
            "points": {
                "exterior": [
                    [
                        665,
                        349
                    ],
                    [
                        668,
                        354
                    ],
                    [
                        672,
                        360
                    ],
                    [
                        672,
                        366
                    ],
                    [
                        672,
                        371
                    ],
                    [
                        675,
                        376
                    ],
                    [
                        677,
                        373
                    ],
                    [
                        678,
                        367
                    ],
                    [
                        677,
                        361
                    ],
                    [
                        674,
                        356
                    ],
                    [
                        672,
                        352
                    ],
                    [
                        669,
                        349
                    ]
                ],
                "interior": []
            }
        }
    ]
}